organize_my_photos.py
Organize_my_photos-1.0.7.dist-info/LICENSE
Organize_my_photos-1.0.7.dist-info/METADATA
Organize_my_photos-1.0.7.dist-info/WHEEL
Organize_my_photos-1.0.7.dist-info/entry_points.txt
Organize_my_photos-1.0.7.dist-info/top_level.txt
Organize_my_photos-1.0.7.dist-info/RECORD
