Metadata-Version: 2.1
Name: Organize-my-photos
Version: 1.0.7
Summary: Terminal program that organizes and organizes the photographs in folders by year, month and day.
Home-page: https://github.com/tanrax/organize-my-photos
Author: Andros Fenollosa
Author-email: andros@fenollosa.email
License: UNKNOWN
Keywords: jpg,jpeg,sort,organize
Platform: UNKNOWN
Classifier: Programming Language :: Python :: 3
Classifier: License :: OSI Approved :: MIT License
Classifier: Operating System :: OS Independent
Requires-Python: >3.6
Requires-Dist: Click (>=6.7)
